h5db
