Metadata-Version: 2.1
Name: h5db
Version: 0.1.2
Summary: 利用h5来做一个分布式的kv磁盘存储工具
Home-page: https://www.zhihu.com/people/feifeiaphy
Author: Larryjianfeng
Author-email: 244060203@qq.com
License: UNKNOWN
Platform: UNKNOWN
